{
    "name": "产品中心",
    "slug": "products",
    "container_mode": "fullwidth",
    "blocks": [
        {
            "id": "block_cebcece7-a3cc-4a33-b869-eda2c2959ab0",
            "type": "shortcode",
            "title": "全站眉页",
            "content": "[csop_header]",
            "collapsed": false,
            "sort": 1
        },
        {
            "id": "block_24c26d37-a962-40dd-80f4-428067a45186",
            "type": "shortcode",
            "title": "产品询盘系统",
            "content": "[csop_products]",
            "collapsed": false,
            "sort": 2
        },
        {
            "id": "block_8f70f240-9c1a-4385-b734-9c849e62b2da",
            "type": "shortcode",
            "title": "全站脚页",
            "content": "[csop_footer]",
            "collapsed": false,
            "sort": 3
        }
    ]
}